LICENSE
MANIFEST.in
README.rst
requirements.txt
setup.cfg
setup.py
tox.ini
ansible_tower_cli.egg-info/PKG-INFO
ansible_tower_cli.egg-info/SOURCES.txt
ansible_tower_cli.egg-info/dependency_links.txt
ansible_tower_cli.egg-info/entry_points.txt
ansible_tower_cli.egg-info/not-zip-safe
ansible_tower_cli.egg-info/requires.txt
ansible_tower_cli.egg-info/top_level.txt
docs/Makefile
docs/README.md
docs/source/CONTRIBUTING.rst
docs/source/HISTORY.rst
docs/source/conf.py
docs/source/index.rst
docs/source/install.rst
docs/source/quickstart.rst
docs/source/api_ref/conf.rst
docs/source/api_ref/exceptions.rst
docs/source/api_ref/generate_tables.py
docs/source/api_ref/index.rst
docs/source/api_ref/resources/ad_hoc.rst
docs/source/api_ref/resources/application.rst
docs/source/api_ref/resources/credential.rst
docs/source/api_ref/resources/credential_type.rst
docs/source/api_ref/resources/group.rst
docs/source/api_ref/resources/host.rst
docs/source/api_ref/resources/instance.rst
docs/source/api_ref/resources/instance_group.rst
docs/source/api_ref/resources/inventory.rst
docs/source/api_ref/resources/inventory_script.rst
docs/source/api_ref/resources/inventory_source.rst
docs/source/api_ref/resources/inventory_update.rst
docs/source/api_ref/resources/job.rst
docs/source/api_ref/resources/job_template.rst
docs/source/api_ref/resources/label.rst
docs/source/api_ref/resources/node.rst
docs/source/api_ref/resources/notification_template.rst
docs/source/api_ref/resources/organization.rst
docs/source/api_ref/resources/project.rst
docs/source/api_ref/resources/project_update.rst
docs/source/api_ref/resources/role.rst
docs/source/api_ref/resources/schedule.rst
docs/source/api_ref/resources/setting.rst
docs/source/api_ref/resources/team.rst
docs/source/api_ref/resources/user.rst
docs/source/api_ref/resources/workflow.rst
docs/source/api_ref/resources/workflow_job.rst
docs/source/cli_ref/index.rst
docs/source/cli_ref/examples/README.rst
docs/source/cli_ref/examples/fake_data_creator.sh
docs/source/cli_ref/examples/inventory_script_example.py
docs/source/cli_ref/examples/teardown_script.sh
docs/source/cli_ref/examples/variables.yml
docs/source/cli_ref/examples/workflow_demo.sh
docs/source/cli_ref/examples/data/schema_a.yml
docs/source/cli_ref/examples/data/schema_b.yml
