Metadata-Version: 1.1
Name: ansible-tower-cli
Version: 3.3.4
Summary: A CLI tool for Ansible Tower and AWX.
Home-page: https://github.com/ansible/tower-cli
Author: Red Hat, Inc.
Author-email: info@ansible.com
License: Apache 2.0
Platform: UNKNOWN
Classifier: Development Status :: 5 - Production/Stable
Classifier: Environment :: Console
Classifier: Intended Audience :: Developers
Classifier: Intended Audience :: System Administrators
Classifier: License :: OSI Approved :: Apache Software License
Classifier: Operating System :: MacOS :: MacOS X
Classifier: Operating System :: POSIX :: Linux
Classifier: Programming Language :: Python
Classifier: Programming Language :: Python :: 2.7
Classifier: Programming Language :: Python :: 3.4
Classifier: Programming Language :: Python :: 3.5
Classifier: Programming Language :: Python :: 3.6
Classifier: Topic :: System :: Software Distribution
Classifier: Topic :: System :: Systems Administration
Provides: tower_cli
